pydantic_firebase/__init__.py
pydantic_firebase/db_collection.py
pydantic_firebase/db_document.py
pydantic_firebase/db_reference.py
pydantic_firebase/utils.py
pydantic_firebase-0.1.1.dist-info/METADATA
pydantic_firebase-0.1.1.dist-info/WHEEL
pydantic_firebase-0.1.1.dist-info/RECORD
